src/__init__.py
src/bedrock_client.py
src/config.py
src/input_handler.py
src/models.py
src/sample_code_gen.py
src/server.py
src/translation_engine.py
bedrock_translation_mcp-0.1.0.dist-info/METADATA
bedrock_translation_mcp-0.1.0.dist-info/WHEEL
bedrock_translation_mcp-0.1.0.dist-info/entry_points.txt
bedrock_translation_mcp-0.1.0.dist-info/RECORD
