Metadata-Version: 2.4
Name: bedrock-translation-mcp
Version: 0.1.0
Summary: Translation MCP Server using AWS Bedrock Nova Pro
Requires-Python: >=3.10
Requires-Dist: boto3>=1.34.0
Requires-Dist: mcp>=0.1.0
Requires-Dist: python-dotenv>=1.0.0
Provides-Extra: dev
Requires-Dist: hypothesis>=6.92.0; extra == 'dev'
Requires-Dist: pytest-asyncio>=0.21.0; extra == 'dev'
Requires-Dist: pytest>=7.4.0; extra == 'dev'
